pyui_design/__init__.py
pyui_design/cli/__init__.py
pyui_design/lib/__init__.py
pyui_design/lib/constants/__init__.py
pyui_design/lib/constants/http.py
pyui_design/lib/constants/service.py
pyui_design/lib/utils/__init__.py
pyui_design/lib/utils/string.py
pyui_design/model/__init__.py
pyui_design-0.0.3.dist-info/LICENSE
pyui_design-0.0.3.dist-info/METADATA
pyui_design-0.0.3.dist-info/WHEEL
pyui_design-0.0.3.dist-info/top_level.txt
pyui_design-0.0.3.dist-info/RECORD
