Metadata-Version: 2.1
Name: pyui-design
Version: 0.0.3
Summary: A Python User Interface package
Author-email: yuanjun <yj@shenkuan.com.cn>
Project-URL: Homepage, https://pyui.design
Project-URL: Issues, https://pyui.design/issues
Classifier: Programming Language :: Python :: 3
Classifier: License :: OSI Approved :: MIT License
Classifier: Operating System :: OS Independent
Requires-Python: >=3.4
License-File: LICENSE
